QcloudApi/__init__.py
QcloudApi/qcloudapi.py
QcloudApi/common/__init__.py
QcloudApi/common/api_exception.py
QcloudApi/common/request.py
QcloudApi/common/sign.py
QcloudApi/modules/__init__.py
QcloudApi/modules/account.py
QcloudApi/modules/apigateway.py
QcloudApi/modules/athena.py
QcloudApi/modules/base.py
QcloudApi/modules/batch.py
QcloudApi/modules/bgpip.py
QcloudApi/modules/bill.py
QcloudApi/modules/bm.py
QcloudApi/modules/bmeip.py
QcloudApi/modules/bmlb.py
QcloudApi/modules/bmvpc.py
QcloudApi/modules/cbs.py
QcloudApi/modules/ccr.py
QcloudApi/modules/ccs.py
QcloudApi/modules/cdb.py
QcloudApi/modules/cdn.py
QcloudApi/modules/cloudaudit.py
QcloudApi/modules/cmem.py
QcloudApi/modules/cns.py
QcloudApi/modules/cvm.py
QcloudApi/modules/dc.py
QcloudApi/modules/dfw.py
QcloudApi/modules/eip.py
QcloudApi/modules/emr.py
QcloudApi/modules/feecenter.py
QcloudApi/modules/image.py
QcloudApi/modules/lb.py
QcloudApi/modules/live.py
QcloudApi/modules/market.py
QcloudApi/modules/monitor.py
QcloudApi/modules/partners.py
QcloudApi/modules/redis.py
QcloudApi/modules/scaling.py
QcloudApi/modules/scf.py
QcloudApi/modules/sec.py
QcloudApi/modules/snapshot.py
QcloudApi/modules/sts.py
QcloudApi/modules/tbaas.py
QcloudApi/modules/tdsql.py
QcloudApi/modules/tmt.py
QcloudApi/modules/trade.py
QcloudApi/modules/vod.py
QcloudApi/modules/vpc.py
QcloudApi/modules/wenzhi.py
QcloudApi/modules/yunsou.py
tencentcloud/__init__.py
tencentcloud/aai/__init__.py
tencentcloud/aai/v20180522/__init__.py
tencentcloud/aai/v20180522/aai_client.py
tencentcloud/aai/v20180522/aai_client_async.py
tencentcloud/aai/v20180522/errorcodes.py
tencentcloud/aai/v20180522/models.py
tencentcloud/aca/__init__.py
tencentcloud/aca/v20210323/__init__.py
tencentcloud/aca/v20210323/aca_client.py
tencentcloud/aca/v20210323/aca_client_async.py
tencentcloud/aca/v20210323/errorcodes.py
tencentcloud/aca/v20210323/models.py
tencentcloud/acp/__init__.py
tencentcloud/acp/v20220105/__init__.py
tencentcloud/acp/v20220105/acp_client.py
tencentcloud_sdk_python-3.1.41.dist-info/LICENSE
tencentcloud_sdk_python-3.1.41.dist-info/METADATA
tencentcloud_sdk_python-3.1.41.dist-info/WHEEL
tencentcloud_sdk_python-3.1.41.dist-info/top_level.txt
tencentcloud_sdk_python-3.1.41.dist-info/RECORD
