Metadata-Version: 2.1
Name: tencentcloud-sdk-python
Version: 3.1.41
Summary: Tencent Cloud SDK for Python
Home-page: https://github.com/TencentCloud/tencentcloud-sdk-python
Author: Tencent Cloud
Maintainer-email: tencentcloudapi@tencent.com
License: Apache License 2.0
Platform: any
Classifier: Development Status :: 5 - Production/Stable
Classifier: Intended Audience :: Developers
Classifier: License :: OSI Approved :: Apache Software License
Classifier: Programming Language :: Python
Classifier: Programming Language :: Python :: 2.7
Classifier: Programming Language :: Python :: 3
Classifier: Programming Language :: Python :: 3.7
Classifier: Programming Language :: Python :: 3.8
Classifier: Programming Language :: Python :: 3.9
Classifier: Programming Language :: Python :: 3.10
Classifier: Programming Language :: Python :: 3.11
Classifier: Programming Language :: Python :: 3.12
License-File: LICENSE
Requires-Dist: requests >=2.16.0
Provides-Extra: async
Requires-Dist: httpx >=0.22.0 ; extra == 'async'
